ivimfit/__init__.py
ivimfit/adc.py
ivimfit/bayesian.py
ivimfit/biexp.py
ivimfit/segmented.py
ivimfit/synthetic.py
ivimfit/triexp.py
ivimfit/utils.py
ivimfit-0.1.5.dist-info/licenses/LICENSE
ivimfit-0.1.5.dist-info/METADATA
ivimfit-0.1.5.dist-info/WHEEL
ivimfit-0.1.5.dist-info/top_level.txt
ivimfit-0.1.5.dist-info/RECORD
