Metadata-Version: 2.4
Name: ivimfit
Version: 0.1.5
Summary: A Python library for IVIM diffusion MRI model fitting
Author-email: Atakan Işık <atakani@baskent.edu.tr>
License-Expression: MIT
Requires-Python: >=3.8
License-File: LICENSE
Requires-Dist: numpy>=1.21
Requires-Dist: scipy>=1.7
Requires-Dist: matplotlib>=3.4
Requires-Dist: pymc>=5.0
Requires-Dist: pytensor>=2.12
Dynamic: license-file
